tcpsocket/__init__.py
tcpsocket/echoclient.py
tcpsocket/echoserver.py
tcpsocket/ipaddr.py
tcpsocket/tcpclient.py
tcpsocket/tcpserver.py
tcpsocket/udpclient.py
tcpsocket/udpserver.py
tcpsocket/xmlrpcclient.py
tcpsocket/xmlrpcserver.py
tcpsocket-1.4.dist-info/METADATA
tcpsocket-1.4.dist-info/WHEEL
tcpsocket-1.4.dist-info/top_level.txt
tcpsocket-1.4.dist-info/RECORD
